cppgsh/__init__.py
cppgsh/cppgsh.py
cppgsh-0.2.1.dist-info/LICENSE
cppgsh-0.2.1.dist-info/METADATA
cppgsh-0.2.1.dist-info/WHEEL
cppgsh-0.2.1.dist-info/entry_points.txt
cppgsh-0.2.1.dist-info/top_level.txt
cppgsh-0.2.1.dist-info/RECORD
