Metadata-Version: 2.1
Name: cppgsh
Version: 0.2.1
Summary: Single header generator for C++ libraries.
Home-page: https://github.com/kirin123kirin/cppgsh
Author: kirin123kirin
License: MIT
Keywords: singleheader,c++,cplus,cpp,hpp
Platform: UNKNOWN
Classifier: Programming Language :: Python :: 3
Classifier: Programming Language :: Python :: 3.6
Classifier: Programming Language :: Python :: 3.7
Classifier: Programming Language :: Python :: 3.8
Classifier: Programming Language :: Python :: 3.9
Classifier: Programming Language :: Python :: 3.10
Classifier: License :: OSI Approved :: MIT License
License-File: LICENSE
Requires-Dist: setuptools (>=42)
Requires-Dist: wheel
Requires-Dist: quom
Provides-Extra: test
Requires-Dist: pytest ; extra == 'test'
Requires-Dist: pytest-cov ; extra == 'test'
Requires-Dist: psutil ; extra == 'test'
